rocketmq/__init__.py
rocketmq/grpc_protocol/__init__.py
rocketmq/grpc_protocol/admin_pb2.py
rocketmq/grpc_protocol/admin_pb2_grpc.py
rocketmq/grpc_protocol/definition_pb2.py
rocketmq/grpc_protocol/definition_pb2_grpc.py
rocketmq/grpc_protocol/service_pb2.py
rocketmq/grpc_protocol/service_pb2_grpc.py
rocketmq/v5/__init__.py
rocketmq/v5/client/__init__.py
rocketmq/v5/client/client.py
rocketmq/v5/client/client_configuration.py
rocketmq/v5/client/scheduler.py
rocketmq/v5/client/balancer/__init__.py
rocketmq/v5/client/balancer/queue_selector.py
rocketmq/v5/client/connection/__init__.py
rocketmq/v5/client/connection/rpc_channel.py
rocketmq/v5/client/connection/rpc_client.py
rocketmq/v5/client/metrics/__init__.py
rocketmq/v5/client/metrics/client_metrics.py
rocketmq/v5/consumer/__init__.py
rocketmq/v5/consumer/consumer.py
rocketmq/v5/consumer/push/__init__.py
rocketmq/v5/consumer/push/consumption.py
rocketmq/v5/consumer/push/fifo_consumption.py
rocketmq/v5/consumer/push/lite_push_consumer.py
rocketmq/v5/consumer/push/message_listener.py
rocketmq/v5/consumer/push/push_consumer.py
rocketmq/v5/consumer/simple/__init__.py
rocketmq/v5/consumer/simple/simple_consumer.py
rocketmq/v5/exception/__init__.py
rocketmq/v5/exception/client_exception.py
rocketmq/v5/log/__init__.py
rocketmq/v5/log/log_config.py
rocketmq/v5/model/__init__.py
rocketmq/v5/model/assignment.py
rocketmq/v5/model/callback_result.py
rocketmq/v5/model/filter_expression.py
rocketmq/v5/model/message.py
rocketmq/v5/model/metrics.py
rocketmq/v5/model/process_queue.py
rocketmq/v5/model/retry_policy.py
rocketmq/v5/model/send_receipt.py
rocketmq/v5/model/topic_route.py
rocketmq/v5/producer/__init__.py
rocketmq/v5/producer/producer.py
rocketmq/v5/test/__init__.py
rocketmq/v5/test/test_base.py
rocketmq/v5/test/test_consumer.py
rocketmq/v5/test/test_producer.py
rocketmq/v5/util/__init__.py
rocketmq/v5/util/atomic.py
rocketmq/v5/util/client_id.py
rocketmq/v5/util/concurrent_map.py
rocketmq/v5/util/message_id_codec.py
rocketmq_python_client-5.1.0.dist-info/licenses/LICENSE
rocketmq_python_client-5.1.0.dist-info/licenses/NOTICE
rocketmq_python_client-5.1.0.dist-info/METADATA
rocketmq_python_client-5.1.0.dist-info/WHEEL
rocketmq_python_client-5.1.0.dist-info/top_level.txt
rocketmq_python_client-5.1.0.dist-info/RECORD
