Metadata-Version: 2.4
Name: rocketmq-python-client
Version: 5.1.0
Requires-Python: >=3.7
License-File: LICENSE
License-File: NOTICE
Requires-Dist: grpcio>=1.5.0
Requires-Dist: grpcio-tools>=1.5.0
Requires-Dist: protobuf
Requires-Dist: opentelemetry-api>=1.33.0
Requires-Dist: opentelemetry-sdk>=1.33.0
Requires-Dist: opentelemetry-exporter-otlp>=1.33.0
Dynamic: license-file
Dynamic: requires-dist
Dynamic: requires-python
